sitelogparser/__init__.py
sitelogparser/common/__init__.py
sitelogparser/common/generate.py
sitelogparser/common/sitelog.py
sitelogparser/common/time_window.py
sitelogparser/tests/__init__.py
sitelogparser/tests/test_parser.py
SiteLogParser-1.1.5.dist-info/LICENSE.txt
SiteLogParser-1.1.5.dist-info/METADATA
SiteLogParser-1.1.5.dist-info/WHEEL
SiteLogParser-1.1.5.dist-info/top_level.txt
SiteLogParser-1.1.5.dist-info/RECORD
